filebrowser_safe/__init__.py
filebrowser_safe/base.py
filebrowser_safe/fields.py
filebrowser_safe/forms.py
filebrowser_safe/functions.py
filebrowser_safe/models.py
filebrowser_safe/settings.py
filebrowser_safe/storage.py
filebrowser_safe/urls.py
filebrowser_safe/views.py
filebrowser_safe/locale/ar/LC_MESSAGES/django.mo
filebrowser_safe/locale/ar/LC_MESSAGES/django.po
filebrowser_safe/locale/ca/LC_MESSAGES/django.mo
filebrowser_safe/locale/ca/LC_MESSAGES/django.po
filebrowser_safe/locale/cs/LC_MESSAGES/django.mo
filebrowser_safe/locale/cs/LC_MESSAGES/django.po
filebrowser_safe/locale/de/LC_MESSAGES/django.mo
filebrowser_safe/locale/de/LC_MESSAGES/django.po
filebrowser_safe/locale/es/LC_MESSAGES/django.mo
filebrowser_safe/locale/es/LC_MESSAGES/django.po
filebrowser_safe/locale/fr/LC_MESSAGES/django.mo
filebrowser_safe/locale/fr/LC_MESSAGES/django.po
filebrowser_safe/locale/it/LC_MESSAGES/django.mo
filebrowser_safe/locale/it/LC_MESSAGES/django.po
filebrowser_safe/locale/nb/LC_MESSAGES/django.mo
filebrowser_safe/locale/nb/LC_MESSAGES/django.po
filebrowser_safe/locale/nl/LC_MESSAGES/django.mo
filebrowser_safe/locale/nl/LC_MESSAGES/django.po
filebrowser_safe/locale/ru/LC_MESSAGES/django.mo
filebrowser_safe/locale/ru/LC_MESSAGES/django.po
filebrowser_safe/locale/sr/LC_MESSAGES/django.mo
filebrowser_safe/locale/sr/LC_MESSAGES/django.po
filebrowser_safe/locale/sr_Latn/LC_MESSAGES/django.mo
filebrowser_safe/locale/sr_Latn/LC_MESSAGES/django.po
filebrowser_safe/locale/zh_CN/LC_MESSAGES/django.mo
filebrowser_safe/locale/zh_CN/LC_MESSAGES/django.po
filebrowser_safe/locale/zh_TW/LC_MESSAGES/django.mo
filebrowser_safe/locale/zh_TW/LC_MESSAGES/django.po
filebrowser_safe/static/filebrowser/css/filebrowser.css
filebrowser_safe/static/filebrowser/css/rtl.css
filebrowser_safe/static/filebrowser/img/filebrowser_icon_delete.gif
filebrowser_safe/static/filebrowser/img/filebrowser_icon_delete_hover.gif
filebrowser_safe/static/filebrowser/img/filebrowser_icon_rename.gif
filebrowser_safe-1.1.1.dist-info/LICENSE
filebrowser_safe-1.1.1.dist-info/METADATA
filebrowser_safe-1.1.1.dist-info/WHEEL
filebrowser_safe-1.1.1.dist-info/top_level.txt
filebrowser_safe-1.1.1.dist-info/RECORD
