Metadata-Version: 2.1
Name: filebrowser-safe
Version: 1.1.1
Summary: A snapshot of the filebrowser_3 branch of django-filebrowser, packaged as a dependency for the Mezzanine CMS for Django.
Home-page: http://github.com/stephenmcd/filebrowser-safe
Author: Patrick Kranzlmueller, Axel Swoboda (vonautomatisch)
Author-email: werkstaetten@vonautomatisch.at
Maintainer: Stephen McDonald
Maintainer-email: stephen.mc@gmail.com
License: UNKNOWN
Platform: UNKNOWN
Classifier: Programming Language :: Python
Classifier: Programming Language :: Python :: 3
Classifier: Programming Language :: Python :: 3.6
Classifier: Programming Language :: Python :: 3.7
Classifier: Programming Language :: Python :: 3.8
Classifier: Programming Language :: Python :: 3.9
Classifier: Programming Language :: Python :: 3.10
Requires-Python: >=3.6
License-File: LICENSE
Provides-Extra: codestyle
Requires-Dist: flake8 (<4,>=3) ; extra == 'codestyle'
Requires-Dist: black (==20.8b1) ; extra == 'codestyle'
Requires-Dist: isort (<6,>=5) ; extra == 'codestyle'
Requires-Dist: pyupgrade (<3,>=2) ; extra == 'codestyle'
Provides-Extra: testing
Requires-Dist: pytest-django (<5,>=4) ; extra == 'testing'
Requires-Dist: pytest-cov (<3,>=2) ; extra == 'testing'
